twitter_2_album/__init__.py
twitter_2_album/allowlist
twitter_2_album-0.0.31.dist-info/LICENSE
twitter_2_album-0.0.31.dist-info/METADATA
twitter_2_album-0.0.31.dist-info/WHEEL
twitter_2_album-0.0.31.dist-info/top_level.txt
twitter_2_album-0.0.31.dist-info/RECORD
